{
    "args": {
        "model": "llama_8b",
        "dataset": "multisocial_en",
        "token_mode": "last_token",
        "ood": true,
        "smoke_test": false,
        "pca": false,
        "model_name": "llama_8b"
    },
    "test_metrics": {
        "test_metrics_by_layer": [
            {
                "n_total": 500,
                "auroc": 0.7150319999999999,
                "accuracy": 0.68,
                "f1": 0.6747967479674797,
                "tpr_at_fpr_0_05": 0.068,
                "optimal_threshold_f1": 0.5,
                "optimal_threshold_acc": 0.5,
                "aupr": 0.7028616423492546
            },
            {
                "n_total": 500,
                "auroc": 0.778736,
                "accuracy": 0.672,
                "f1": 0.5638297872340425,
                "tpr_at_fpr_0_05": 0.312,
                "optimal_threshold_f1": 0.5,
                "optimal_threshold_acc": 0.5,
                "aupr": 0.7623633234949556
            },
            {
                "n_total": 500,
                "auroc": 0.7797599999999999,
                "accuracy": 0.672,
                "f1": 0.5661375661375662,
                "tpr_at_fpr_0_05": 0.328,
                "optimal_threshold_f1": 0.5,
                "optimal_threshold_acc": 0.5,
                "aupr": 0.7619927714142101
            },
            {
                "n_total": 500,
                "auroc": 0.858944,
                "accuracy": 0.77,
                "f1": 0.7319347319347319,
                "tpr_at_fpr_0_05": 0.512,
                "optimal_threshold_f1": 0.5,
                "optimal_threshold_acc": 0.5,
                "aupr": 0.872576275148202
            },
            {
                "n_total": 500,
                "auroc": 0.866736,
                "accuracy": 0.782,
                "f1": 0.7423167848699763,
                "tpr_at_fpr_0_05": 0.544,
                "optimal_threshold_f1": 0.5,
                "optimal_threshold_acc": 0.5,
                "aupr": 0.8794816019339309
            },
            {
                "n_total": 500,
                "auroc": 0.8891039999999999,
                "accuracy": 0.782,
                "f1": 0.7435294117647059,
                "tpr_at_fpr_0_05": 0.548,
                "optimal_threshold_f1": 0.5,
                "optimal_threshold_acc": 0.5,
                "aupr": 0.8971289157408946
            },
            {
                "n_total": 500,
                "auroc": 0.882528,
                "accuracy": 0.772,
                "f1": 0.7361111111111112,
                "tpr_at_fpr_0_05": 0.528,
                "optimal_threshold_f1": 0.5,
                "optimal_threshold_acc": 0.5,
                "aupr": 0.8838792358891135
            },
            {
                "n_total": 500,
                "auroc": 0.893728,
                "accuracy": 0.778,
                "f1": 0.7388235294117647,
                "tpr_at_fpr_0_05": 0.564,
                "optimal_threshold_f1": 0.5,
                "optimal_threshold_acc": 0.5,
                "aupr": 0.8988729952357466
            },
            {
                "n_total": 500,
                "auroc": 0.8947359999999999,
                "accuracy": 0.78,
                "f1": 0.7368421052631579,
                "tpr_at_fpr_0_05": 0.588,
                "optimal_threshold_f1": 0.5,
                "optimal_threshold_acc": 0.5,
                "aupr": 0.9020296562152696
            },
            {
                "n_total": 500,
                "auroc": 0.8996799999999999,
                "accuracy": 0.762,
                "f1": 0.7017543859649122,
                "tpr_at_fpr_0_05": 0.592,
                "optimal_threshold_f1": 0.5,
                "optimal_threshold_acc": 0.5,
                "aupr": 0.9010299536318294
            },
            {
                "n_total": 500,
                "auroc": 0.91592,
                "accuracy": 0.774,
                "f1": 0.7250608272506083,
                "tpr_at_fpr_0_05": 0.596,
                "optimal_threshold_f1": 0.5,
                "optimal_threshold_acc": 0.5,
                "aupr": 0.9165754284297606
            },
            {
                "n_total": 500,
                "auroc": 0.9087999999999999,
                "accuracy": 0.78,
                "f1": 0.7380952380952381,
                "tpr_at_fpr_0_05": 0.6,
                "optimal_threshold_f1": 0.5,
                "optimal_threshold_acc": 0.5,
                "aupr": 0.911169551681072
            },
            {
                "n_total": 500,
                "auroc": 0.9041920000000001,
                "accuracy": 0.78,
                "f1": 0.7417840375586855,
                "tpr_at_fpr_0_05": 0.568,
                "optimal_threshold_f1": 0.5,
                "optimal_threshold_acc": 0.5,
                "aupr": 0.9034957675712006
            },
            {
                "n_total": 500,
                "auroc": 0.9002880000000001,
                "accuracy": 0.766,
                "f1": 0.7167070217917676,
                "tpr_at_fpr_0_05": 0.544,
                "optimal_threshold_f1": 0.5,
                "optimal_threshold_acc": 0.5,
                "aupr": 0.8938277529880027
            },
            {
                "n_total": 500,
                "auroc": 0.9021600000000001,
                "accuracy": 0.792,
                "f1": 0.7570093457943925,
                "tpr_at_fpr_0_05": 0.54,
                "optimal_threshold_f1": 0.5,
                "optimal_threshold_acc": 0.5,
                "aupr": 0.9025690359500906
            },
            {
                "n_total": 500,
                "auroc": 0.890432,
                "accuracy": 0.776,
                "f1": 0.7383177570093458,
                "tpr_at_fpr_0_05": 0.504,
                "optimal_threshold_f1": 0.5,
                "optimal_threshold_acc": 0.5,
                "aupr": 0.8939471002564311
            },
            {
                "n_total": 500,
                "auroc": 0.880976,
                "accuracy": 0.736,
                "f1": 0.6796116504854369,
                "tpr_at_fpr_0_05": 0.488,
                "optimal_threshold_f1": 0.5,
                "optimal_threshold_acc": 0.5,
                "aupr": 0.8866742151295732
            },
            {
                "n_total": 500,
                "auroc": 0.905168,
                "accuracy": 0.778,
                "f1": 0.7400468384074942,
                "tpr_at_fpr_0_05": 0.52,
                "optimal_threshold_f1": 0.5,
                "optimal_threshold_acc": 0.5,
                "aupr": 0.9015040931355626
            },
            {
                "n_total": 500,
                "auroc": 0.901152,
                "accuracy": 0.792,
                "f1": 0.7603686635944701,
                "tpr_at_fpr_0_05": 0.548,
                "optimal_threshold_f1": 0.5,
                "optimal_threshold_acc": 0.5,
                "aupr": 0.9056006665303022
            },
            {
                "n_total": 500,
                "auroc": 0.9122720000000001,
                "accuracy": 0.8,
                "f1": 0.7695852534562212,
                "tpr_at_fpr_0_05": 0.62,
                "optimal_threshold_f1": 0.5,
                "optimal_threshold_acc": 0.5,
                "aupr": 0.906905164847588
            },
            {
                "n_total": 500,
                "auroc": 0.90544,
                "accuracy": 0.778,
                "f1": 0.7412587412587412,
                "tpr_at_fpr_0_05": 0.548,
                "optimal_threshold_f1": 0.5,
                "optimal_threshold_acc": 0.5,
                "aupr": 0.8929075063388117
            },
            {
                "n_total": 500,
                "auroc": 0.913376,
                "accuracy": 0.804,
                "f1": 0.7772727272727272,
                "tpr_at_fpr_0_05": 0.652,
                "optimal_threshold_f1": 0.5,
                "optimal_threshold_acc": 0.5,
                "aupr": 0.911011570096983
            },
            {
                "n_total": 500,
                "auroc": 0.9066719999999999,
                "accuracy": 0.794,
                "f1": 0.765375854214123,
                "tpr_at_fpr_0_05": 0.564,
                "optimal_threshold_f1": 0.5,
                "optimal_threshold_acc": 0.5,
                "aupr": 0.8962045003642225
            },
            {
                "n_total": 500,
                "auroc": 0.907712,
                "accuracy": 0.804,
                "f1": 0.7841409691629956,
                "tpr_at_fpr_0_05": 0.536,
                "optimal_threshold_f1": 0.5,
                "optimal_threshold_acc": 0.5,
                "aupr": 0.8980124780895081
            },
            {
                "n_total": 500,
                "auroc": 0.9037120000000001,
                "accuracy": 0.812,
                "f1": 0.7947598253275109,
                "tpr_at_fpr_0_05": 0.496,
                "optimal_threshold_f1": 0.5,
                "optimal_threshold_acc": 0.5,
                "aupr": 0.8953278983289634
            },
            {
                "n_total": 500,
                "auroc": 0.9126400000000001,
                "accuracy": 0.824,
                "f1": 0.808695652173913,
                "tpr_at_fpr_0_05": 0.592,
                "optimal_threshold_f1": 0.5,
                "optimal_threshold_acc": 0.5,
                "aupr": 0.9116448942868698
            },
            {
                "n_total": 500,
                "auroc": 0.9040160000000002,
                "accuracy": 0.812,
                "f1": 0.7965367965367965,
                "tpr_at_fpr_0_05": 0.556,
                "optimal_threshold_f1": 0.5,
                "optimal_threshold_acc": 0.5,
                "aupr": 0.902658430727548
            },
            {
                "n_total": 500,
                "auroc": 0.911296,
                "accuracy": 0.824,
                "f1": 0.8103448275862069,
                "tpr_at_fpr_0_05": 0.552,
                "optimal_threshold_f1": 0.5,
                "optimal_threshold_acc": 0.5,
                "aupr": 0.9095565091336008
            },
            {
                "n_total": 500,
                "auroc": 0.895184,
                "accuracy": 0.79,
                "f1": 0.7608200455580866,
                "tpr_at_fpr_0_05": 0.576,
                "optimal_threshold_f1": 0.5,
                "optimal_threshold_acc": 0.5,
                "aupr": 0.8983418447497322
            },
            {
                "n_total": 500,
                "auroc": 0.9036160000000001,
                "accuracy": 0.808,
                "f1": 0.7931034482758621,
                "tpr_at_fpr_0_05": 0.564,
                "optimal_threshold_f1": 0.5,
                "optimal_threshold_acc": 0.5,
                "aupr": 0.9054254582597134
            },
            {
                "n_total": 500,
                "auroc": 0.903712,
                "accuracy": 0.812,
                "f1": 0.7947598253275109,
                "tpr_at_fpr_0_05": 0.576,
                "optimal_threshold_f1": 0.5,
                "optimal_threshold_acc": 0.5,
                "aupr": 0.9070701864129966
            },
            {
                "n_total": 500,
                "auroc": 0.905328,
                "accuracy": 0.8,
                "f1": 0.7777777777777778,
                "tpr_at_fpr_0_05": 0.544,
                "optimal_threshold_f1": 0.5,
                "optimal_threshold_acc": 0.5,
                "aupr": 0.9034874000371688
            },
            {
                "n_total": 500,
                "auroc": 0.90096,
                "accuracy": 0.792,
                "f1": 0.7719298245614035,
                "tpr_at_fpr_0_05": 0.488,
                "optimal_threshold_f1": 0.5,
                "optimal_threshold_acc": 0.5,
                "aupr": 0.8993882972874134
            }
        ],
        "mean_projection_metrics": {
            "n_total": 500,
            "auroc": 0.936992,
            "accuracy": 0.812,
            "f1": 0.780373831775701,
            "tpr_at_fpr_0_05": 0.696,
            "optimal_threshold_f1": 0.5,
            "optimal_threshold_acc": 0.5,
            "aupr": 0.9409538071917902
        },
        "weighted_projection_metrics": {
            "n_total": 500,
            "auroc": 0.937072,
            "accuracy": 0.814,
            "f1": 0.7832167832167832,
            "tpr_at_fpr_0_05": 0.696,
            "optimal_threshold_f1": 0.5,
            "optimal_threshold_acc": 0.5,
            "aupr": 0.9409117670794325
        },
        "meta_pca_metrics": {
            "n_total": 500,
            "auroc": 0.8557600000000001,
            "accuracy": 0.776,
            "f1": 0.7488789237668162,
            "tpr_at_fpr_0_05": 0.444,
            "optimal_threshold_f1": 0.5,
            "optimal_threshold_acc": 0.5,
            "aupr": 0.8485276339659183
        }
    }
}