{
  "args": {
    "model": "llama_8b",
    "dataset": "multisocial_en",
    "mode": "ldp",
    "token_mode": "last_token",
    "prefix": false,
    "smoke_test": false,
    "ood": [
      "multisocial_de",
      "multisocial_nl",
      "multisocial_pt",
      "multisocial_ar"
    ],
    "pca_components": 20,
    "normalize_scores": true,
    "manifold": true
  },
  "steering_domain": "multisocial_en",
  "eval_domain": "multisocial_de",
  "n_samples": 500,
  "n_layers": 33,
  "metrics_per_layer": {
    "layer_1": {
      "n_total": 500,
      "n_valid": 500,
      "n_val_total": 500,
      "n_val_valid": 500,
      "acc": 0.7,
      "f1": 0.6666666666666666,
      "pre": 0.75,
      "recall": 0.6,
      "auroc": 0.716064,
      "optimal_threshold": 0.5432752370834351,
      "tpr_at_fpr_0_01": 0.0,
      "fpr95": 0.94,
      "aupr": 0.7230193917584267
    },
    "layer_2": {
      "n_total": 500,
      "n_valid": 500,
      "n_val_total": 500,
      "n_val_valid": 500,
      "acc": 0.694,
      "f1": 0.6909090909090909,
      "pre": 0.6979591836734694,
      "recall": 0.684,
      "auroc": 0.7402719999999999,
      "optimal_threshold": 0.48281732201576233,
      "tpr_at_fpr_0_01": 0.068,
      "fpr95": 0.852,
      "aupr": 0.7460464038455918
    },
    "layer_3": {
      "n_total": 500,
      "n_valid": 500,
      "n_val_total": 500,
      "n_val_valid": 500,
      "acc": 0.694,
      "f1": 0.6921529175050302,
      "pre": 0.6963562753036437,
      "recall": 0.688,
      "auroc": 0.7534719999999999,
      "optimal_threshold": 0.41635528206825256,
      "tpr_at_fpr_0_01": 0.084,
      "fpr95": 0.804,
      "aupr": 0.7605770326590605
    },
    "layer_4": {
      "n_total": 500,
      "n_valid": 500,
      "n_val_total": 500,
      "n_val_valid": 500,
      "acc": 0.714,
      "f1": 0.6829268292682927,
      "pre": 0.7661691542288557,
      "recall": 0.616,
      "auroc": 0.7707200000000001,
      "optimal_threshold": 0.5893803834915161,
      "tpr_at_fpr_0_01": 0.152,
      "fpr95": 0.776,
      "aupr": 0.790090851372656
    },
    "layer_5": {
      "n_total": 500,
      "n_valid": 500,
      "n_val_total": 500,
      "n_val_valid": 500,
      "acc": 0.702,
      "f1": 0.6965376782077393,
      "pre": 0.7095435684647303,
      "recall": 0.684,
      "auroc": 0.783952,
      "optimal_threshold": 0.3910786807537079,
      "tpr_at_fpr_0_01": 0.168,
      "fpr95": 0.708,
      "aupr": 0.7990951895379517
    },
    "layer_6": {
      "n_total": 500,
      "n_valid": 500,
      "n_val_total": 500,
      "n_val_valid": 500,
      "acc": 0.722,
      "f1": 0.7110187110187111,
      "pre": 0.7402597402597403,
      "recall": 0.684,
      "auroc": 0.7876960000000001,
      "optimal_threshold": 0.37779757380485535,
      "tpr_at_fpr_0_01": 0.22,
      "fpr95": 0.752,
      "aupr": 0.8084963919178485
    },
    "layer_7": {
      "n_total": 500,
      "n_valid": 500,
      "n_val_total": 500,
      "n_val_valid": 500,
      "acc": 0.72,
      "f1": 0.7095435684647303,
      "pre": 0.7370689655172413,
      "recall": 0.684,
      "auroc": 0.7885759999999999,
      "optimal_threshold": 0.3891342580318451,
      "tpr_at_fpr_0_01": 0.184,
      "fpr95": 0.756,
      "aupr": 0.8013296370626526
    },
    "layer_8": {
      "n_total": 500,
      "n_valid": 500,
      "n_val_total": 500,
      "n_val_valid": 500,
      "acc": 0.714,
      "f1": 0.7014613778705637,
      "pre": 0.7336244541484717,
      "recall": 0.672,
      "auroc": 0.7938399999999999,
      "optimal_threshold": 0.3934802711009979,
      "tpr_at_fpr_0_01": 0.228,
      "fpr95": 0.708,
      "aupr": 0.8108200876089241
    },
    "layer_9": {
      "n_total": 500,
      "n_valid": 500,
      "n_val_total": 500,
      "n_val_valid": 500,
      "acc": 0.726,
      "f1": 0.6806526806526807,
      "pre": 0.8156424581005587,
      "recall": 0.584,
      "auroc": 0.79,
      "optimal_threshold": 0.49170124530792236,
      "tpr_at_fpr_0_01": 0.252,
      "fpr95": 0.752,
      "aupr": 0.8100420716910816
    },
    "layer_10": {
      "n_total": 500,
      "n_valid": 500,
      "n_val_total": 500,
      "n_val_valid": 500,
      "acc": 0.718,
      "f1": 0.6634844868735084,
      "pre": 0.8224852071005917,
      "recall": 0.556,
      "auroc": 0.804544,
      "optimal_threshold": 0.484262615442276,
      "tpr_at_fpr_0_01": 0.264,
      "fpr95": 0.692,
      "aupr": 0.8195669633859939
    },
    "layer_11": {
      "n_total": 500,
      "n_valid": 500,
      "n_val_total": 500,
      "n_val_valid": 500,
      "acc": 0.722,
      "f1": 0.6904231625835189,
      "pre": 0.7788944723618091,
      "recall": 0.62,
      "auroc": 0.8160799999999999,
      "optimal_threshold": 0.40956446528434753,
      "tpr_at_fpr_0_01": 0.192,
      "fpr95": 0.632,
      "aupr": 0.8263513701276199
    },
    "layer_12": {
      "n_total": 500,
      "n_valid": 500,
      "n_val_total": 500,
      "n_val_valid": 500,
      "acc": 0.724,
      "f1": 0.6933333333333334,
      "pre": 0.78,
      "recall": 0.624,
      "auroc": 0.8109919999999999,
      "optimal_threshold": 0.40189820528030396,
      "tpr_at_fpr_0_01": 0.176,
      "fpr95": 0.752,
      "aupr": 0.8183131545618328
    },
    "layer_13": {
      "n_total": 500,
      "n_valid": 500,
      "n_val_total": 500,
      "n_val_valid": 500,
      "acc": 0.73,
      "f1": 0.6924829157175398,
      "pre": 0.8042328042328042,
      "recall": 0.608,
      "auroc": 0.81104,
      "optimal_threshold": 0.42330124974250793,
      "tpr_at_fpr_0_01": 0.228,
      "fpr95": 0.696,
      "aupr": 0.8274837549951615
    },
    "layer_14": {
      "n_total": 500,
      "n_valid": 500,
      "n_val_total": 500,
      "n_val_valid": 500,
      "acc": 0.744,
      "f1": 0.7288135593220338,
      "pre": 0.7747747747747747,
      "recall": 0.688,
      "auroc": 0.8080960000000001,
      "optimal_threshold": 0.3444668650627136,
      "tpr_at_fpr_0_01": 0.228,
      "fpr95": 0.684,
      "aupr": 0.8186959249207548
    },
    "layer_15": {
      "n_total": 500,
      "n_valid": 500,
      "n_val_total": 500,
      "n_val_valid": 500,
      "acc": 0.74,
      "f1": 0.7357723577235772,
      "pre": 0.7479338842975206,
      "recall": 0.724,
      "auroc": 0.823328,
      "optimal_threshold": 0.2907552421092987,
      "tpr_at_fpr_0_01": 0.24,
      "fpr95": 0.644,
      "aupr": 0.8321298927708505
    },
    "layer_16": {
      "n_total": 500,
      "n_valid": 500,
      "n_val_total": 500,
      "n_val_valid": 500,
      "acc": 0.712,
      "f1": 0.6742081447963801,
      "pre": 0.7760416666666666,
      "recall": 0.596,
      "auroc": 0.8091520000000001,
      "optimal_threshold": 0.39443156123161316,
      "tpr_at_fpr_0_01": 0.244,
      "fpr95": 0.704,
      "aupr": 0.8237742728729205
    },
    "layer_17": {
      "n_total": 500,
      "n_valid": 500,
      "n_val_total": 500,
      "n_val_valid": 500,
      "acc": 0.724,
      "f1": 0.703862660944206,
      "pre": 0.7592592592592593,
      "recall": 0.656,
      "auroc": 0.8017920000000001,
      "optimal_threshold": 0.34985804557800293,
      "tpr_at_fpr_0_01": 0.244,
      "fpr95": 0.752,
      "aupr": 0.8190913170239222
    },
    "layer_18": {
      "n_total": 500,
      "n_valid": 500,
      "n_val_total": 500,
      "n_val_valid": 500,
      "acc": 0.718,
      "f1": 0.6954643628509719,
      "pre": 0.755868544600939,
      "recall": 0.644,
      "auroc": 0.788752,
      "optimal_threshold": 0.36893942952156067,
      "tpr_at_fpr_0_01": 0.248,
      "fpr95": 0.772,
      "aupr": 0.8135945861105277
    },
    "layer_19": {
      "n_total": 500,
      "n_valid": 500,
      "n_val_total": 500,
      "n_val_valid": 500,
      "acc": 0.728,
      "f1": 0.7142857142857143,
      "pre": 0.7522123893805309,
      "recall": 0.68,
      "auroc": 0.780224,
      "optimal_threshold": 0.32964545488357544,
      "tpr_at_fpr_0_01": 0.24,
      "fpr95": 0.796,
      "aupr": 0.8108828903793094
    },
    "layer_20": {
      "n_total": 500,
      "n_valid": 500,
      "n_val_total": 500,
      "n_val_valid": 500,
      "acc": 0.716,
      "f1": 0.7041666666666667,
      "pre": 0.7347826086956522,
      "recall": 0.676,
      "auroc": 0.767008,
      "optimal_threshold": 0.3492709994316101,
      "tpr_at_fpr_0_01": 0.22,
      "fpr95": 0.828,
      "aupr": 0.8006270383882303
    },
    "layer_21": {
      "n_total": 500,
      "n_valid": 500,
      "n_val_total": 500,
      "n_val_valid": 500,
      "acc": 0.718,
      "f1": 0.7068607068607069,
      "pre": 0.7359307359307359,
      "recall": 0.68,
      "auroc": 0.759728,
      "optimal_threshold": 0.3564331829547882,
      "tpr_at_fpr_0_01": 0.228,
      "fpr95": 0.856,
      "aupr": 0.7986579253875417
    },
    "layer_22": {
      "n_total": 500,
      "n_valid": 500,
      "n_val_total": 500,
      "n_val_valid": 500,
      "acc": 0.72,
      "f1": 0.6759259259259259,
      "pre": 0.8021978021978022,
      "recall": 0.584,
      "auroc": 0.763472,
      "optimal_threshold": 0.4658675193786621,
      "tpr_at_fpr_0_01": 0.176,
      "fpr95": 0.872,
      "aupr": 0.7984379767005968
    },
    "layer_23": {
      "n_total": 500,
      "n_valid": 500,
      "n_val_total": 500,
      "n_val_valid": 500,
      "acc": 0.722,
      "f1": 0.6744730679156908,
      "pre": 0.8135593220338984,
      "recall": 0.576,
      "auroc": 0.7574720000000001,
      "optimal_threshold": 0.46610012650489807,
      "tpr_at_fpr_0_01": 0.2,
      "fpr95": 0.916,
      "aupr": 0.7941954512315126
    },
    "layer_24": {
      "n_total": 500,
      "n_valid": 500,
      "n_val_total": 500,
      "n_val_valid": 500,
      "acc": 0.716,
      "f1": 0.6858407079646017,
      "pre": 0.7673267326732673,
      "recall": 0.62,
      "auroc": 0.752768,
      "optimal_threshold": 0.42053478956222534,
      "tpr_at_fpr_0_01": 0.2,
      "fpr95": 0.928,
      "aupr": 0.7889084647048495
    },
    "layer_25": {
      "n_total": 500,
      "n_valid": 500,
      "n_val_total": 500,
      "n_val_valid": 500,
      "acc": 0.722,
      "f1": 0.6729411764705883,
      "pre": 0.8171428571428572,
      "recall": 0.572,
      "auroc": 0.7480479999999999,
      "optimal_threshold": 0.45680704712867737,
      "tpr_at_fpr_0_01": 0.192,
      "fpr95": 0.92,
      "aupr": 0.7851101905027017
    },
    "layer_26": {
      "n_total": 500,
      "n_valid": 500,
      "n_val_total": 500,
      "n_val_valid": 500,
      "acc": 0.71,
      "f1": 0.648910411622276,
      "pre": 0.8220858895705522,
      "recall": 0.536,
      "auroc": 0.751648,
      "optimal_threshold": 0.47525718808174133,
      "tpr_at_fpr_0_01": 0.192,
      "fpr95": 0.908,
      "aupr": 0.7846023451518706
    },
    "layer_27": {
      "n_total": 500,
      "n_valid": 500,
      "n_val_total": 500,
      "n_val_valid": 500,
      "acc": 0.732,
      "f1": 0.7242798353909465,
      "pre": 0.7457627118644068,
      "recall": 0.704,
      "auroc": 0.751168,
      "optimal_threshold": 0.33988505601882935,
      "tpr_at_fpr_0_01": 0.152,
      "fpr95": 0.924,
      "aupr": 0.7836446123597892
    },
    "layer_28": {
      "n_total": 500,
      "n_valid": 500,
      "n_val_total": 500,
      "n_val_valid": 500,
      "acc": 0.73,
      "f1": 0.7227926078028748,
      "pre": 0.7426160337552743,
      "recall": 0.704,
      "auroc": 0.74496,
      "optimal_threshold": 0.35511714220046997,
      "tpr_at_fpr_0_01": 0.108,
      "fpr95": 0.948,
      "aupr": 0.7757354837924498
    },
    "layer_29": {
      "n_total": 500,
      "n_valid": 500,
      "n_val_total": 500,
      "n_val_valid": 500,
      "acc": 0.736,
      "f1": 0.7066666666666667,
      "pre": 0.795,
      "recall": 0.636,
      "auroc": 0.7686559999999999,
      "optimal_threshold": 0.41041502356529236,
      "tpr_at_fpr_0_01": 0.176,
      "fpr95": 0.896,
      "aupr": 0.7936571199499789
    },
    "layer_30": {
      "n_total": 500,
      "n_valid": 500,
      "n_val_total": 500,
      "n_val_valid": 500,
      "acc": 0.742,
      "f1": 0.7213822894168467,
      "pre": 0.784037558685446,
      "recall": 0.668,
      "auroc": 0.771168,
      "optimal_threshold": 0.3910059928894043,
      "tpr_at_fpr_0_01": 0.184,
      "fpr95": 0.888,
      "aupr": 0.7946579476901484
    },
    "layer_31": {
      "n_total": 500,
      "n_valid": 500,
      "n_val_total": 500,
      "n_val_valid": 500,
      "acc": 0.744,
      "f1": 0.7155555555555555,
      "pre": 0.805,
      "recall": 0.644,
      "auroc": 0.772928,
      "optimal_threshold": 0.42020079493522644,
      "tpr_at_fpr_0_01": 0.152,
      "fpr95": 0.876,
      "aupr": 0.7940256154962271
    },
    "layer_32": {
      "n_total": 500,
      "n_valid": 500,
      "n_val_total": 500,
      "n_val_valid": 500,
      "acc": 0.74,
      "f1": 0.7149122807017544,
      "pre": 0.7912621359223301,
      "recall": 0.652,
      "auroc": 0.7982879999999999,
      "optimal_threshold": 0.4150298237800598,
      "tpr_at_fpr_0_01": 0.192,
      "fpr95": 0.684,
      "aupr": 0.799794902368134
    },
    "layer_33": {
      "n_total": 500,
      "n_valid": 500,
      "n_val_total": 500,
      "n_val_valid": 500,
      "acc": 0.676,
      "f1": 0.6954887218045113,
      "pre": 0.6560283687943262,
      "recall": 0.74,
      "auroc": 0.783056,
      "optimal_threshold": 0.4267243444919586,
      "tpr_at_fpr_0_01": 0.1,
      "fpr95": 0.72,
      "aupr": 0.7758435794953286
    }
  },
  "metrics_avg_projection": {
    "n_total": 500,
    "n_valid": 500,
    "n_val_total": 500,
    "n_val_valid": 500,
    "acc": 0.7,
    "f1": 0.70703125,
    "pre": 0.6908396946564885,
    "recall": 0.724,
    "auroc": 0.7881440000000001,
    "optimal_threshold": 0.31511232256889343,
    "tpr_at_fpr_0_01": 0.284,
    "fpr95": 0.716,
    "aupr": 0.8146231701785134
  },
  "metrics_avg_projection_div_std": {
    "n_total": 500,
    "n_valid": 500,
    "n_val_total": 500,
    "n_val_valid": 500,
    "acc": 0.656,
    "f1": 0.5473684210526316,
    "pre": 0.8,
    "recall": 0.416,
    "auroc": 0.735104,
    "optimal_threshold": 6.204511642456055,
    "tpr_at_fpr_0_01": 0.024,
    "fpr95": 0.908,
    "aupr": 0.7284091836928734
  },
  "metrics_avg_projection_last_2_3_layers": {
    "n_total": 500,
    "n_valid": 500,
    "n_val_total": 500,
    "n_val_valid": 500,
    "acc": 0.74,
    "f1": 0.7222222222222222,
    "pre": 0.7752293577981652,
    "recall": 0.676,
    "auroc": 0.7845119999999999,
    "optimal_threshold": 0.37126797437667847,
    "tpr_at_fpr_0_01": 0.248,
    "fpr95": 0.796,
    "aupr": 0.8137858283888777
  },
  "metrics_avg_projection_div_std_last_2_3_layers": {
    "n_total": 500,
    "n_valid": 500,
    "n_val_total": 500,
    "n_val_valid": 500,
    "acc": 0.694,
    "f1": 0.6805845511482255,
    "pre": 0.7117903930131004,
    "recall": 0.652,
    "auroc": 0.719024,
    "optimal_threshold": 8.137557983398438,
    "tpr_at_fpr_0_01": 0.032,
    "fpr95": 0.924,
    "aupr": 0.7170366472596716
  }
}