{
  "args": {
    "model": "llama_8b",
    "dataset": "multisocial_en",
    "mode": "logistic_m",
    "token_mode": "last_token",
    "prefix": false,
    "smoke_test": false,
    "ood": [
      "multisocial_de",
      "multisocial_nl",
      "multisocial_pt",
      "multisocial_ar"
    ],
    "normalize_scores": true,
    "pca_components": 10,
    "ablation_set": "all",
    "manifold": true
  },
  "steering_domain": "multisocial_en",
  "eval_domain": "multisocial_ar",
  "n_samples": 500,
  "n_layers": 33,
  "metrics_per_layer": {
    "layer_1": {
      "n_total": 500,
      "n_valid": 500,
      "n_val_total": 500,
      "n_val_valid": 500,
      "acc": 0.67,
      "f1": 0.5728900255754475,
      "pre": 0.7943262411347518,
      "recall": 0.448,
      "auroc": 0.701096,
      "optimal_threshold": 0.36,
      "optimal_threshold_f1": 0.36,
      "optimal_threshold_acc": 0.391,
      "best_f1_on_threshold_sweep": 0.7565392354124749,
      "best_acc_on_threshold_sweep": 0.76,
      "tpr_at_fpr_0_01": 0.0,
      "fpr95": 0.88,
      "aupr": 0.7185182206863878
    },
    "layer_2": {
      "n_total": 500,
      "n_valid": 500,
      "n_val_total": 500,
      "n_val_valid": 500,
      "acc": 0.664,
      "f1": 0.5670103092783505,
      "pre": 0.7971014492753623,
      "recall": 0.44,
      "auroc": 0.67648,
      "optimal_threshold": 0.46,
      "optimal_threshold_f1": 0.46,
      "optimal_threshold_acc": 0.487,
      "best_f1_on_threshold_sweep": 0.7865168539325842,
      "best_acc_on_threshold_sweep": 0.776,
      "tpr_at_fpr_0_01": 0.136,
      "fpr95": 0.86,
      "aupr": 0.7279696557756635
    },
    "layer_3": {
      "n_total": 500,
      "n_valid": 500,
      "n_val_total": 500,
      "n_val_valid": 500,
      "acc": 0.658,
      "f1": 0.583756345177665,
      "pre": 0.7986111111111112,
      "recall": 0.46,
      "auroc": 0.75808,
      "optimal_threshold": 0.464,
      "optimal_threshold_f1": 0.464,
      "optimal_threshold_acc": 0.531,
      "best_f1_on_threshold_sweep": 0.8115384615384615,
      "best_acc_on_threshold_sweep": 0.808,
      "tpr_at_fpr_0_01": 0.036,
      "fpr95": 0.672,
      "aupr": 0.7520225604145034
    },
    "layer_4": {
      "n_total": 500,
      "n_valid": 500,
      "n_val_total": 500,
      "n_val_valid": 500,
      "acc": 0.652,
      "f1": 0.583756345177665,
      "pre": 0.7986111111111112,
      "recall": 0.46,
      "auroc": 0.7303999999999999,
      "optimal_threshold": 0.439,
      "optimal_threshold_f1": 0.439,
      "optimal_threshold_acc": 0.504,
      "best_f1_on_threshold_sweep": 0.8169014084507042,
      "best_acc_on_threshold_sweep": 0.82,
      "tpr_at_fpr_0_01": 0.06,
      "fpr95": 0.88,
      "aupr": 0.7496905970479877
    },
    "layer_5": {
      "n_total": 500,
      "n_valid": 500,
      "n_val_total": 500,
      "n_val_valid": 500,
      "acc": 0.658,
      "f1": 0.5390835579514824,
      "pre": 0.8264462809917356,
      "recall": 0.4,
      "auroc": 0.755552,
      "optimal_threshold": 0.406,
      "optimal_threshold_f1": 0.406,
      "optimal_threshold_acc": 0.406,
      "best_f1_on_threshold_sweep": 0.8362068965517242,
      "best_acc_on_threshold_sweep": 0.848,
      "tpr_at_fpr_0_01": 0.092,
      "fpr95": 0.796,
      "aupr": 0.7647713832831758
    },
    "layer_6": {
      "n_total": 500,
      "n_valid": 500,
      "n_val_total": 500,
      "n_val_valid": 500,
      "acc": 0.668,
      "f1": 0.5699481865284974,
      "pre": 0.8088235294117647,
      "recall": 0.44,
      "auroc": 0.7242560000000001,
      "optimal_threshold": 0.314,
      "optimal_threshold_f1": 0.314,
      "optimal_threshold_acc": 0.314,
      "best_f1_on_threshold_sweep": 0.8429752066115703,
      "best_acc_on_threshold_sweep": 0.848,
      "tpr_at_fpr_0_01": 0.144,
      "fpr95": 0.872,
      "aupr": 0.7503197685598328
    },
    "layer_7": {
      "n_total": 500,
      "n_valid": 500,
      "n_val_total": 500,
      "n_val_valid": 500,
      "acc": 0.686,
      "f1": 0.624390243902439,
      "pre": 0.8,
      "recall": 0.512,
      "auroc": 0.7256959999999999,
      "optimal_threshold": 0.314,
      "optimal_threshold_f1": 0.314,
      "optimal_threshold_acc": 0.323,
      "best_f1_on_threshold_sweep": 0.8662674650698602,
      "best_acc_on_threshold_sweep": 0.868,
      "tpr_at_fpr_0_01": 0.08,
      "fpr95": 0.808,
      "aupr": 0.7475474259252407
    },
    "layer_8": {
      "n_total": 500,
      "n_valid": 500,
      "n_val_total": 500,
      "n_val_valid": 500,
      "acc": 0.694,
      "f1": 0.6462264150943396,
      "pre": 0.7873563218390804,
      "recall": 0.548,
      "auroc": 0.7315200000000001,
      "optimal_threshold": 0.29,
      "optimal_threshold_f1": 0.29,
      "optimal_threshold_acc": 0.302,
      "best_f1_on_threshold_sweep": 0.8525896414342629,
      "best_acc_on_threshold_sweep": 0.854,
      "tpr_at_fpr_0_01": 0.068,
      "fpr95": 0.812,
      "aupr": 0.749331772178706
    },
    "layer_9": {
      "n_total": 500,
      "n_valid": 500,
      "n_val_total": 500,
      "n_val_valid": 500,
      "acc": 0.682,
      "f1": 0.7010309278350515,
      "pre": 0.723404255319149,
      "recall": 0.68,
      "auroc": 0.757008,
      "optimal_threshold": 0.28,
      "optimal_threshold_f1": 0.28,
      "optimal_threshold_acc": 0.338,
      "best_f1_on_threshold_sweep": 0.8293577981651377,
      "best_acc_on_threshold_sweep": 0.838,
      "tpr_at_fpr_0_01": 0.088,
      "fpr95": 0.772,
      "aupr": 0.7646840509746349
    },
    "layer_10": {
      "n_total": 500,
      "n_valid": 500,
      "n_val_total": 500,
      "n_val_valid": 500,
      "acc": 0.682,
      "f1": 0.6521739130434783,
      "pre": 0.823170731707317,
      "recall": 0.54,
      "auroc": 0.8012319999999999,
      "optimal_threshold": 0.341,
      "optimal_threshold_f1": 0.341,
      "optimal_threshold_acc": 0.365,
      "best_f1_on_threshold_sweep": 0.8612244897959184,
      "best_acc_on_threshold_sweep": 0.87,
      "tpr_at_fpr_0_01": 0.112,
      "fpr95": 0.672,
      "aupr": 0.8018535833754921
    },
    "layer_11": {
      "n_total": 500,
      "n_valid": 500,
      "n_val_total": 500,
      "n_val_valid": 500,
      "acc": 0.724,
      "f1": 0.6584158415841584,
      "pre": 0.8636363636363636,
      "recall": 0.532,
      "auroc": 0.840128,
      "optimal_threshold": 0.315,
      "optimal_threshold_f1": 0.315,
      "optimal_threshold_acc": 0.315,
      "best_f1_on_threshold_sweep": 0.8708333333333333,
      "best_acc_on_threshold_sweep": 0.876,
      "tpr_at_fpr_0_01": 0.112,
      "fpr95": 0.648,
      "aupr": 0.8285540817133128
    },
    "layer_12": {
      "n_total": 500,
      "n_valid": 500,
      "n_val_total": 500,
      "n_val_valid": 500,
      "acc": 0.718,
      "f1": 0.6808510638297872,
      "pre": 0.8323699421965318,
      "recall": 0.576,
      "auroc": 0.839456,
      "optimal_threshold": 0.3,
      "optimal_threshold_f1": 0.3,
      "optimal_threshold_acc": 0.312,
      "best_f1_on_threshold_sweep": 0.8582995951417004,
      "best_acc_on_threshold_sweep": 0.862,
      "tpr_at_fpr_0_01": 0.104,
      "fpr95": 0.616,
      "aupr": 0.8237521856772791
    },
    "layer_13": {
      "n_total": 500,
      "n_valid": 500,
      "n_val_total": 500,
      "n_val_valid": 500,
      "acc": 0.716,
      "f1": 0.7450980392156863,
      "pre": 0.8181818181818182,
      "recall": 0.684,
      "auroc": 0.8322559999999999,
      "optimal_threshold": 0.298,
      "optimal_threshold_f1": 0.298,
      "optimal_threshold_acc": 0.343,
      "best_f1_on_threshold_sweep": 0.8647619047619047,
      "best_acc_on_threshold_sweep": 0.866,
      "tpr_at_fpr_0_01": 0.092,
      "fpr95": 0.704,
      "aupr": 0.82322350469784
    },
    "layer_14": {
      "n_total": 500,
      "n_valid": 500,
      "n_val_total": 500,
      "n_val_valid": 500,
      "acc": 0.704,
      "f1": 0.6354679802955665,
      "pre": 0.8269230769230769,
      "recall": 0.516,
      "auroc": 0.824544,
      "optimal_threshold": 0.306,
      "optimal_threshold_f1": 0.306,
      "optimal_threshold_acc": 0.306,
      "best_f1_on_threshold_sweep": 0.8606060606060605,
      "best_acc_on_threshold_sweep": 0.862,
      "tpr_at_fpr_0_01": 0.092,
      "fpr95": 0.744,
      "aupr": 0.8190981060111999
    },
    "layer_15": {
      "n_total": 500,
      "n_valid": 500,
      "n_val_total": 500,
      "n_val_valid": 500,
      "acc": 0.736,
      "f1": 0.6886792452830188,
      "pre": 0.8390804597701149,
      "recall": 0.584,
      "auroc": 0.842608,
      "optimal_threshold": 0.279,
      "optimal_threshold_f1": 0.279,
      "optimal_threshold_acc": 0.279,
      "best_f1_on_threshold_sweep": 0.8640973630831643,
      "best_acc_on_threshold_sweep": 0.866,
      "tpr_at_fpr_0_01": 0.084,
      "fpr95": 0.712,
      "aupr": 0.8307286590203202
    },
    "layer_16": {
      "n_total": 500,
      "n_valid": 500,
      "n_val_total": 500,
      "n_val_valid": 500,
      "acc": 0.754,
      "f1": 0.7185354691075515,
      "pre": 0.839572192513369,
      "recall": 0.628,
      "auroc": 0.84296,
      "optimal_threshold": 0.28300000000000003,
      "optimal_threshold_f1": 0.28300000000000003,
      "optimal_threshold_acc": 0.28300000000000003,
      "best_f1_on_threshold_sweep": 0.8605577689243028,
      "best_acc_on_threshold_sweep": 0.86,
      "tpr_at_fpr_0_01": 0.104,
      "fpr95": 0.688,
      "aupr": 0.8359924437175117
    },
    "layer_17": {
      "n_total": 500,
      "n_valid": 500,
      "n_val_total": 500,
      "n_val_valid": 500,
      "acc": 0.746,
      "f1": 0.6954436450839329,
      "pre": 0.8682634730538922,
      "recall": 0.58,
      "auroc": 0.8503040000000001,
      "optimal_threshold": 0.296,
      "optimal_threshold_f1": 0.296,
      "optimal_threshold_acc": 0.296,
      "best_f1_on_threshold_sweep": 0.8600405679513186,
      "best_acc_on_threshold_sweep": 0.862,
      "tpr_at_fpr_0_01": 0.148,
      "fpr95": 0.7,
      "aupr": 0.8448347478199606
    },
    "layer_18": {
      "n_total": 500,
      "n_valid": 500,
      "n_val_total": 500,
      "n_val_valid": 500,
      "acc": 0.78,
      "f1": 0.7533632286995515,
      "pre": 0.8571428571428571,
      "recall": 0.672,
      "auroc": 0.87896,
      "optimal_threshold": 0.267,
      "optimal_threshold_f1": 0.267,
      "optimal_threshold_acc": 0.267,
      "best_f1_on_threshold_sweep": 0.8683693516699411,
      "best_acc_on_threshold_sweep": 0.866,
      "tpr_at_fpr_0_01": 0.172,
      "fpr95": 0.504,
      "aupr": 0.8597788700200278
    },
    "layer_19": {
      "n_total": 500,
      "n_valid": 500,
      "n_val_total": 500,
      "n_val_valid": 500,
      "acc": 0.748,
      "f1": 0.7511111111111111,
      "pre": 0.845,
      "recall": 0.676,
      "auroc": 0.8708960000000001,
      "optimal_threshold": 0.259,
      "optimal_threshold_f1": 0.259,
      "optimal_threshold_acc": 0.28,
      "best_f1_on_threshold_sweep": 0.8588235294117647,
      "best_acc_on_threshold_sweep": 0.86,
      "tpr_at_fpr_0_01": 0.16,
      "fpr95": 0.512,
      "aupr": 0.8526906106454064
    },
    "layer_20": {
      "n_total": 500,
      "n_valid": 500,
      "n_val_total": 500,
      "n_val_valid": 500,
      "acc": 0.76,
      "f1": 0.7627494456762749,
      "pre": 0.8557213930348259,
      "recall": 0.688,
      "auroc": 0.880096,
      "optimal_threshold": 0.246,
      "optimal_threshold_f1": 0.246,
      "optimal_threshold_acc": 0.266,
      "best_f1_on_threshold_sweep": 0.8717948717948719,
      "best_acc_on_threshold_sweep": 0.872,
      "tpr_at_fpr_0_01": 0.164,
      "fpr95": 0.456,
      "aupr": 0.8592057261374925
    },
    "layer_21": {
      "n_total": 500,
      "n_valid": 500,
      "n_val_total": 500,
      "n_val_valid": 500,
      "acc": 0.766,
      "f1": 0.7259953161592506,
      "pre": 0.8757062146892656,
      "recall": 0.62,
      "auroc": 0.860352,
      "optimal_threshold": 0.25,
      "optimal_threshold_f1": 0.25,
      "optimal_threshold_acc": 0.25,
      "best_f1_on_threshold_sweep": 0.8697394789579158,
      "best_acc_on_threshold_sweep": 0.87,
      "tpr_at_fpr_0_01": 0.148,
      "fpr95": 0.54,
      "aupr": 0.8443904255673313
    },
    "layer_22": {
      "n_total": 500,
      "n_valid": 500,
      "n_val_total": 500,
      "n_val_valid": 500,
      "acc": 0.696,
      "f1": 0.7095238095238096,
      "pre": 0.8764705882352941,
      "recall": 0.596,
      "auroc": 0.8631360000000001,
      "optimal_threshold": 0.272,
      "optimal_threshold_f1": 0.272,
      "optimal_threshold_acc": 0.293,
      "best_f1_on_threshold_sweep": 0.8629856850715746,
      "best_acc_on_threshold_sweep": 0.868,
      "tpr_at_fpr_0_01": 0.172,
      "fpr95": 0.492,
      "aupr": 0.8427614462239922
    },
    "layer_23": {
      "n_total": 500,
      "n_valid": 500,
      "n_val_total": 500,
      "n_val_valid": 500,
      "acc": 0.754,
      "f1": 0.7092198581560284,
      "pre": 0.8670520231213873,
      "recall": 0.6,
      "auroc": 0.8564320000000001,
      "optimal_threshold": 0.277,
      "optimal_threshold_f1": 0.277,
      "optimal_threshold_acc": 0.277,
      "best_f1_on_threshold_sweep": 0.8658536585365854,
      "best_acc_on_threshold_sweep": 0.868,
      "tpr_at_fpr_0_01": 0.164,
      "fpr95": 0.496,
      "aupr": 0.8417337507254203
    },
    "layer_24": {
      "n_total": 500,
      "n_valid": 500,
      "n_val_total": 500,
      "n_val_valid": 500,
      "acc": 0.79,
      "f1": 0.7682119205298014,
      "pre": 0.8571428571428571,
      "recall": 0.696,
      "auroc": 0.867392,
      "optimal_threshold": 0.261,
      "optimal_threshold_f1": 0.261,
      "optimal_threshold_acc": 0.261,
      "best_f1_on_threshold_sweep": 0.87109375,
      "best_acc_on_threshold_sweep": 0.868,
      "tpr_at_fpr_0_01": 0.16,
      "fpr95": 0.5,
      "aupr": 0.8528121516589368
    },
    "layer_25": {
      "n_total": 500,
      "n_valid": 500,
      "n_val_total": 500,
      "n_val_valid": 500,
      "acc": 0.744,
      "f1": 0.6923076923076923,
      "pre": 0.8674698795180723,
      "recall": 0.576,
      "auroc": 0.869424,
      "optimal_threshold": 0.289,
      "optimal_threshold_f1": 0.289,
      "optimal_threshold_acc": 0.289,
      "best_f1_on_threshold_sweep": 0.8727272727272728,
      "best_acc_on_threshold_sweep": 0.874,
      "tpr_at_fpr_0_01": 0.168,
      "fpr95": 0.592,
      "aupr": 0.8619476517758362
    },
    "layer_26": {
      "n_total": 500,
      "n_valid": 500,
      "n_val_total": 500,
      "n_val_valid": 500,
      "acc": 0.722,
      "f1": 0.6498740554156172,
      "pre": 0.8775510204081632,
      "recall": 0.516,
      "auroc": 0.8741759999999998,
      "optimal_threshold": 0.274,
      "optimal_threshold_f1": 0.274,
      "optimal_threshold_acc": 0.274,
      "best_f1_on_threshold_sweep": 0.8646464646464647,
      "best_acc_on_threshold_sweep": 0.866,
      "tpr_at_fpr_0_01": 0.148,
      "fpr95": 0.664,
      "aupr": 0.8655580426520195
    },
    "layer_27": {
      "n_total": 500,
      "n_valid": 500,
      "n_val_total": 500,
      "n_val_valid": 500,
      "acc": 0.658,
      "f1": 0.5210084033613446,
      "pre": 0.8691588785046729,
      "recall": 0.372,
      "auroc": 0.8697919999999999,
      "optimal_threshold": 0.262,
      "optimal_threshold_f1": 0.262,
      "optimal_threshold_acc": 0.262,
      "best_f1_on_threshold_sweep": 0.8697478991596639,
      "best_acc_on_threshold_sweep": 0.876,
      "tpr_at_fpr_0_01": 0.12,
      "fpr95": 0.552,
      "aupr": 0.8467547680933468
    },
    "layer_28": {
      "n_total": 500,
      "n_valid": 500,
      "n_val_total": 500,
      "n_val_valid": 500,
      "acc": 0.66,
      "f1": 0.5142857142857142,
      "pre": 0.9,
      "recall": 0.36,
      "auroc": 0.868416,
      "optimal_threshold": 0.352,
      "optimal_threshold_f1": 0.352,
      "optimal_threshold_acc": 0.352,
      "best_f1_on_threshold_sweep": 0.8717948717948718,
      "best_acc_on_threshold_sweep": 0.88,
      "tpr_at_fpr_0_01": 0.152,
      "fpr95": 0.72,
      "aupr": 0.8651515811807277
    },
    "layer_29": {
      "n_total": 500,
      "n_valid": 500,
      "n_val_total": 500,
      "n_val_valid": 500,
      "acc": 0.758,
      "f1": 0.7125890736342043,
      "pre": 0.8771929824561403,
      "recall": 0.6,
      "auroc": 0.8824640000000001,
      "optimal_threshold": 0.3,
      "optimal_threshold_f1": 0.3,
      "optimal_threshold_acc": 0.3,
      "best_f1_on_threshold_sweep": 0.8693877551020408,
      "best_acc_on_threshold_sweep": 0.872,
      "tpr_at_fpr_0_01": 0.084,
      "fpr95": 0.564,
      "aupr": 0.8609787161159592
    },
    "layer_30": {
      "n_total": 500,
      "n_valid": 500,
      "n_val_total": 500,
      "n_val_valid": 500,
      "acc": 0.706,
      "f1": 0.622107969151671,
      "pre": 0.8705035971223022,
      "recall": 0.484,
      "auroc": 0.870912,
      "optimal_threshold": 0.35100000000000003,
      "optimal_threshold_f1": 0.35100000000000003,
      "optimal_threshold_acc": 0.35100000000000003,
      "best_f1_on_threshold_sweep": 0.8677685950413223,
      "best_acc_on_threshold_sweep": 0.872,
      "tpr_at_fpr_0_01": 0.08,
      "fpr95": 0.552,
      "aupr": 0.8536867993215426
    },
    "layer_31": {
      "n_total": 500,
      "n_valid": 500,
      "n_val_total": 500,
      "n_val_valid": 500,
      "acc": 0.618,
      "f1": 0.6015831134564644,
      "pre": 0.8837209302325582,
      "recall": 0.456,
      "auroc": 0.8321759999999999,
      "optimal_threshold": 0.334,
      "optimal_threshold_f1": 0.334,
      "optimal_threshold_acc": 0.361,
      "best_f1_on_threshold_sweep": 0.8640973630831643,
      "best_acc_on_threshold_sweep": 0.87,
      "tpr_at_fpr_0_01": 0.116,
      "fpr95": 0.568,
      "aupr": 0.8262111678569088
    },
    "layer_32": {
      "n_total": 500,
      "n_valid": 500,
      "n_val_total": 500,
      "n_val_valid": 500,
      "acc": 0.72,
      "f1": 0.6601941747572816,
      "pre": 0.8395061728395061,
      "recall": 0.544,
      "auroc": 0.824464,
      "optimal_threshold": 0.377,
      "optimal_threshold_f1": 0.377,
      "optimal_threshold_acc": 0.377,
      "best_f1_on_threshold_sweep": 0.8714859437751004,
      "best_acc_on_threshold_sweep": 0.872,
      "tpr_at_fpr_0_01": 0.124,
      "fpr95": 0.552,
      "aupr": 0.823537529882143
    },
    "layer_33": {
      "n_total": 500,
      "n_valid": 500,
      "n_val_total": 500,
      "n_val_valid": 500,
      "acc": 0.616,
      "f1": 0.39622641509433965,
      "pre": 0.9264705882352942,
      "recall": 0.252,
      "auroc": 0.8034399999999999,
      "optimal_threshold": 0.468,
      "optimal_threshold_f1": 0.468,
      "optimal_threshold_acc": 0.468,
      "best_f1_on_threshold_sweep": 0.8483606557377049,
      "best_acc_on_threshold_sweep": 0.852,
      "tpr_at_fpr_0_01": 0.076,
      "fpr95": 0.708,
      "aupr": 0.8021885629676244
    }
  },
  "metrics_avg_projection": {
    "n_total": 500,
    "n_valid": 500,
    "n_val_total": 500,
    "n_val_valid": 500,
    "acc": 0.736,
    "f1": 0.6826923076923077,
    "pre": 0.8554216867469879,
    "recall": 0.568,
    "auroc": 0.868528,
    "optimal_threshold": 0.31,
    "optimal_threshold_f1": 0.31,
    "optimal_threshold_acc": 0.31,
    "best_f1_on_threshold_sweep": 0.8735177865612649,
    "best_acc_on_threshold_sweep": 0.872,
    "tpr_at_fpr_0_01": 0.148,
    "fpr95": 0.404,
    "aupr": 0.8472261904706351
  },
  "metrics_avg_projection_div_std": {
    "n_total": 500,
    "n_valid": 500,
    "n_val_total": 500,
    "n_val_valid": 500,
    "acc": 0.5,
    "f1": 0.6666666666666666,
    "pre": 0.5,
    "recall": 1.0,
    "auroc": 0.671856,
    "optimal_threshold": 0.913,
    "optimal_threshold_f1": 0.913,
    "optimal_threshold_acc": 0.913,
    "best_f1_on_threshold_sweep": 0.6684491978609626,
    "best_acc_on_threshold_sweep": 0.504,
    "tpr_at_fpr_0_01": 0.044,
    "fpr95": 0.968,
    "aupr": 0.6968899169483963
  },
  "metrics_avg_projection_last_2_3_layers": {
    "n_total": 500,
    "n_valid": 500,
    "n_val_total": 500,
    "n_val_valid": 500,
    "acc": 0.726,
    "f1": 0.656641604010025,
    "pre": 0.8791946308724832,
    "recall": 0.524,
    "auroc": 0.886864,
    "optimal_threshold": 0.306,
    "optimal_threshold_f1": 0.306,
    "optimal_threshold_acc": 0.306,
    "best_f1_on_threshold_sweep": 0.8806584362139918,
    "best_acc_on_threshold_sweep": 0.884,
    "tpr_at_fpr_0_01": 0.164,
    "fpr95": 0.468,
    "aupr": 0.8683435662433322
  },
  "metrics_avg_projection_div_std_last_2_3_layers": {
    "n_total": 500,
    "n_valid": 500,
    "n_val_total": 500,
    "n_val_valid": 500,
    "acc": 0.5,
    "f1": 0.6666666666666666,
    "pre": 0.5,
    "recall": 1.0,
    "auroc": 0.78824,
    "optimal_threshold": 0.405,
    "optimal_threshold_f1": 0.405,
    "optimal_threshold_acc": 0.405,
    "best_f1_on_threshold_sweep": 0.6675567423230975,
    "best_acc_on_threshold_sweep": 0.502,
    "tpr_at_fpr_0_01": 0.032,
    "fpr95": 0.624,
    "aupr": 0.7409751055805378
  }
}