{
  "args": {
    "model": "llama_8b",
    "dataset": "multisocial_en",
    "mode": "ldp_by_layer",
    "token_mode": "last_token",
    "prefix": false,
    "smoke_test": false,
    "ood": [
      "multisocial_ar"
    ],
    "pca_components": 100,
    "normalize_scores": true,
    "ablation_set": "human",
    "manifold": true
  },
  "steering_domain": "multisocial_en",
  "eval_domain": "multisocial_en",
  "n_samples": 500,
  "n_layers": 33,
  "metrics_per_layer": {
    "layer_1": {
      "n_total": 500,
      "n_valid": 500,
      "n_val_total": 500,
      "n_val_valid": 500,
      "acc": 0.728,
      "f1": 0.6977777777777778,
      "pre": 0.785,
      "recall": 0.628,
      "auroc": 0.7787759999999999,
      "optimal_threshold": 0.500493049621582,
      "tpr_at_fpr_0_01": 0.0,
      "fpr95": 0.788,
      "aupr": 0.7866473266604496
    },
    "layer_2": {
      "n_total": 500,
      "n_valid": 500,
      "n_val_total": 500,
      "n_val_valid": 500,
      "acc": 0.728,
      "f1": 0.7235772357723578,
      "pre": 0.7355371900826446,
      "recall": 0.712,
      "auroc": 0.803664,
      "optimal_threshold": 0.4742102324962616,
      "tpr_at_fpr_0_01": 0.36,
      "fpr95": 0.84,
      "aupr": 0.8407898411156024
    },
    "layer_3": {
      "n_total": 500,
      "n_valid": 500,
      "n_val_total": 500,
      "n_val_valid": 500,
      "acc": 0.752,
      "f1": 0.7405857740585774,
      "pre": 0.7763157894736842,
      "recall": 0.708,
      "auroc": 0.8280639999999999,
      "optimal_threshold": 0.4391199052333832,
      "tpr_at_fpr_0_01": 0.32,
      "fpr95": 0.724,
      "aupr": 0.8499032142731247
    },
    "layer_4": {
      "n_total": 500,
      "n_valid": 500,
      "n_val_total": 500,
      "n_val_valid": 500,
      "acc": 0.754,
      "f1": 0.7320261437908496,
      "pre": 0.8038277511961722,
      "recall": 0.672,
      "auroc": 0.8404959999999999,
      "optimal_threshold": 0.5361156463623047,
      "tpr_at_fpr_0_01": 0.444,
      "fpr95": 0.7,
      "aupr": 0.8648604772317767
    },
    "layer_5": {
      "n_total": 500,
      "n_valid": 500,
      "n_val_total": 500,
      "n_val_valid": 500,
      "acc": 0.758,
      "f1": 0.7505154639175258,
      "pre": 0.774468085106383,
      "recall": 0.728,
      "auroc": 0.855264,
      "optimal_threshold": 0.3975904583930969,
      "tpr_at_fpr_0_01": 0.412,
      "fpr95": 0.64,
      "aupr": 0.873344084747604
    },
    "layer_6": {
      "n_total": 500,
      "n_valid": 500,
      "n_val_total": 500,
      "n_val_valid": 500,
      "acc": 0.776,
      "f1": 0.7751004016064257,
      "pre": 0.7782258064516129,
      "recall": 0.772,
      "auroc": 0.8583839999999999,
      "optimal_threshold": 0.37424275279045105,
      "tpr_at_fpr_0_01": 0.424,
      "fpr95": 0.604,
      "aupr": 0.878768604244367
    },
    "layer_7": {
      "n_total": 500,
      "n_valid": 500,
      "n_val_total": 500,
      "n_val_valid": 500,
      "acc": 0.764,
      "f1": 0.7551867219917012,
      "pre": 0.7844827586206896,
      "recall": 0.728,
      "auroc": 0.8644479999999999,
      "optimal_threshold": 0.4026504456996918,
      "tpr_at_fpr_0_01": 0.412,
      "fpr95": 0.56,
      "aupr": 0.8802700347597403
    },
    "layer_8": {
      "n_total": 500,
      "n_valid": 500,
      "n_val_total": 500,
      "n_val_valid": 500,
      "acc": 0.782,
      "f1": 0.7752577319587629,
      "pre": 0.8,
      "recall": 0.752,
      "auroc": 0.8708959999999999,
      "optimal_threshold": 0.4027024209499359,
      "tpr_at_fpr_0_01": 0.412,
      "fpr95": 0.592,
      "aupr": 0.8882420105481252
    },
    "layer_9": {
      "n_total": 500,
      "n_valid": 500,
      "n_val_total": 500,
      "n_val_valid": 500,
      "acc": 0.78,
      "f1": 0.7708333333333334,
      "pre": 0.8043478260869565,
      "recall": 0.74,
      "auroc": 0.8705759999999999,
      "optimal_threshold": 0.3975127339363098,
      "tpr_at_fpr_0_01": 0.372,
      "fpr95": 0.624,
      "aupr": 0.8853164355857672
    },
    "layer_10": {
      "n_total": 500,
      "n_valid": 500,
      "n_val_total": 500,
      "n_val_valid": 500,
      "acc": 0.778,
      "f1": 0.74364896073903,
      "pre": 0.8797814207650273,
      "recall": 0.644,
      "auroc": 0.8794719999999999,
      "optimal_threshold": 0.49907752871513367,
      "tpr_at_fpr_0_01": 0.368,
      "fpr95": 0.592,
      "aupr": 0.8922769017833801
    },
    "layer_11": {
      "n_total": 500,
      "n_valid": 500,
      "n_val_total": 500,
      "n_val_valid": 500,
      "acc": 0.81,
      "f1": 0.7965738758029979,
      "pre": 0.8571428571428571,
      "recall": 0.744,
      "auroc": 0.88872,
      "optimal_threshold": 0.4070702791213989,
      "tpr_at_fpr_0_01": 0.408,
      "fpr95": 0.508,
      "aupr": 0.9031410106376564
    },
    "layer_12": {
      "n_total": 500,
      "n_valid": 500,
      "n_val_total": 500,
      "n_val_valid": 500,
      "acc": 0.8,
      "f1": 0.782608695652174,
      "pre": 0.8571428571428571,
      "recall": 0.72,
      "auroc": 0.8831360000000001,
      "optimal_threshold": 0.4378286600112915,
      "tpr_at_fpr_0_01": 0.396,
      "fpr95": 0.528,
      "aupr": 0.8976625914663621
    },
    "layer_13": {
      "n_total": 500,
      "n_valid": 500,
      "n_val_total": 500,
      "n_val_valid": 500,
      "acc": 0.802,
      "f1": 0.7870967741935484,
      "pre": 0.8511627906976744,
      "recall": 0.732,
      "auroc": 0.880624,
      "optimal_threshold": 0.4375835955142975,
      "tpr_at_fpr_0_01": 0.432,
      "fpr95": 0.548,
      "aupr": 0.897580333189107
    },
    "layer_14": {
      "n_total": 500,
      "n_valid": 500,
      "n_val_total": 500,
      "n_val_valid": 500,
      "acc": 0.8,
      "f1": 0.7925311203319502,
      "pre": 0.8232758620689655,
      "recall": 0.764,
      "auroc": 0.877792,
      "optimal_threshold": 0.3714871406555176,
      "tpr_at_fpr_0_01": 0.392,
      "fpr95": 0.572,
      "aupr": 0.8947785083006088
    },
    "layer_15": {
      "n_total": 500,
      "n_valid": 500,
      "n_val_total": 500,
      "n_val_valid": 500,
      "acc": 0.778,
      "f1": 0.7350835322195705,
      "pre": 0.9112426035502958,
      "recall": 0.616,
      "auroc": 0.8871519999999999,
      "optimal_threshold": 0.48947301506996155,
      "tpr_at_fpr_0_01": 0.336,
      "fpr95": 0.544,
      "aupr": 0.8993474485689625
    },
    "layer_16": {
      "n_total": 500,
      "n_valid": 500,
      "n_val_total": 500,
      "n_val_valid": 500,
      "acc": 0.796,
      "f1": 0.7792207792207793,
      "pre": 0.8490566037735849,
      "recall": 0.72,
      "auroc": 0.87032,
      "optimal_threshold": 0.4233196973800659,
      "tpr_at_fpr_0_01": 0.36,
      "fpr95": 0.604,
      "aupr": 0.8860509368812741
    },
    "layer_17": {
      "n_total": 500,
      "n_valid": 500,
      "n_val_total": 500,
      "n_val_valid": 500,
      "acc": 0.798,
      "f1": 0.7926078028747433,
      "pre": 0.8143459915611815,
      "recall": 0.772,
      "auroc": 0.861152,
      "optimal_threshold": 0.34521299600601196,
      "tpr_at_fpr_0_01": 0.32,
      "fpr95": 0.664,
      "aupr": 0.8780901575167771
    },
    "layer_18": {
      "n_total": 500,
      "n_valid": 500,
      "n_val_total": 500,
      "n_val_valid": 500,
      "acc": 0.802,
      "f1": 0.7983706720977597,
      "pre": 0.8132780082987552,
      "recall": 0.784,
      "auroc": 0.850704,
      "optimal_threshold": 0.3531811535358429,
      "tpr_at_fpr_0_01": 0.268,
      "fpr95": 0.664,
      "aupr": 0.8696380030623718
    },
    "layer_19": {
      "n_total": 500,
      "n_valid": 500,
      "n_val_total": 500,
      "n_val_valid": 500,
      "acc": 0.774,
      "f1": 0.7822736030828517,
      "pre": 0.7546468401486989,
      "recall": 0.812,
      "auroc": 0.8522879999999999,
      "optimal_threshold": 0.2860569357872009,
      "tpr_at_fpr_0_01": 0.312,
      "fpr95": 0.704,
      "aupr": 0.8728572295068522
    },
    "layer_20": {
      "n_total": 500,
      "n_valid": 500,
      "n_val_total": 500,
      "n_val_valid": 500,
      "acc": 0.79,
      "f1": 0.784394250513347,
      "pre": 0.8059071729957806,
      "recall": 0.764,
      "auroc": 0.845456,
      "optimal_threshold": 0.3709009885787964,
      "tpr_at_fpr_0_01": 0.304,
      "fpr95": 0.732,
      "aupr": 0.8674287782196213
    },
    "layer_21": {
      "n_total": 500,
      "n_valid": 500,
      "n_val_total": 500,
      "n_val_valid": 500,
      "acc": 0.786,
      "f1": 0.7829614604462475,
      "pre": 0.7942386831275721,
      "recall": 0.772,
      "auroc": 0.8449599999999999,
      "optimal_threshold": 0.3622998297214508,
      "tpr_at_fpr_0_01": 0.32,
      "fpr95": 0.78,
      "aupr": 0.8677041498331532
    },
    "layer_22": {
      "n_total": 500,
      "n_valid": 500,
      "n_val_total": 500,
      "n_val_valid": 500,
      "acc": 0.78,
      "f1": 0.7689075630252101,
      "pre": 0.8097345132743363,
      "recall": 0.732,
      "auroc": 0.843616,
      "optimal_threshold": 0.40816953778266907,
      "tpr_at_fpr_0_01": 0.312,
      "fpr95": 0.748,
      "aupr": 0.8644824662272539
    },
    "layer_23": {
      "n_total": 500,
      "n_valid": 500,
      "n_val_total": 500,
      "n_val_valid": 500,
      "acc": 0.786,
      "f1": 0.772823779193206,
      "pre": 0.8235294117647058,
      "recall": 0.728,
      "auroc": 0.8440479999999999,
      "optimal_threshold": 0.4190415143966675,
      "tpr_at_fpr_0_01": 0.316,
      "fpr95": 0.772,
      "aupr": 0.8652823321594255
    },
    "layer_24": {
      "n_total": 500,
      "n_valid": 500,
      "n_val_total": 500,
      "n_val_valid": 500,
      "acc": 0.78,
      "f1": 0.7639484978540773,
      "pre": 0.8240740740740741,
      "recall": 0.712,
      "auroc": 0.8398240000000001,
      "optimal_threshold": 0.4272342324256897,
      "tpr_at_fpr_0_01": 0.296,
      "fpr95": 0.816,
      "aupr": 0.8612015657518222
    },
    "layer_25": {
      "n_total": 500,
      "n_valid": 500,
      "n_val_total": 500,
      "n_val_valid": 500,
      "acc": 0.756,
      "f1": 0.7162790697674418,
      "pre": 0.8555555555555555,
      "recall": 0.616,
      "auroc": 0.845248,
      "optimal_threshold": 0.5004231333732605,
      "tpr_at_fpr_0_01": 0.312,
      "fpr95": 0.784,
      "aupr": 0.864696706288709
    },
    "layer_26": {
      "n_total": 500,
      "n_valid": 500,
      "n_val_total": 500,
      "n_val_valid": 500,
      "acc": 0.77,
      "f1": 0.7438752783964365,
      "pre": 0.8391959798994975,
      "recall": 0.668,
      "auroc": 0.8463519999999999,
      "optimal_threshold": 0.47585177421569824,
      "tpr_at_fpr_0_01": 0.28,
      "fpr95": 0.776,
      "aupr": 0.8637121918168088
    },
    "layer_27": {
      "n_total": 500,
      "n_valid": 500,
      "n_val_total": 500,
      "n_val_valid": 500,
      "acc": 0.782,
      "f1": 0.7875243664717348,
      "pre": 0.7680608365019012,
      "recall": 0.808,
      "auroc": 0.847376,
      "optimal_threshold": 0.3346327245235443,
      "tpr_at_fpr_0_01": 0.272,
      "fpr95": 0.764,
      "aupr": 0.8633306273262857
    },
    "layer_28": {
      "n_total": 500,
      "n_valid": 500,
      "n_val_total": 500,
      "n_val_valid": 500,
      "acc": 0.794,
      "f1": 0.7984344422700587,
      "pre": 0.7816091954022989,
      "recall": 0.816,
      "auroc": 0.849136,
      "optimal_threshold": 0.3528137505054474,
      "tpr_at_fpr_0_01": 0.268,
      "fpr95": 0.712,
      "aupr": 0.8639219946088793
    },
    "layer_29": {
      "n_total": 500,
      "n_valid": 500,
      "n_val_total": 500,
      "n_val_valid": 500,
      "acc": 0.804,
      "f1": 0.7975206611570248,
      "pre": 0.8247863247863247,
      "recall": 0.772,
      "auroc": 0.863936,
      "optimal_threshold": 0.39768677949905396,
      "tpr_at_fpr_0_01": 0.272,
      "fpr95": 0.62,
      "aupr": 0.8734004209790689
    },
    "layer_30": {
      "n_total": 500,
      "n_valid": 500,
      "n_val_total": 500,
      "n_val_valid": 500,
      "acc": 0.808,
      "f1": 0.8016528925619835,
      "pre": 0.8290598290598291,
      "recall": 0.776,
      "auroc": 0.8691039999999999,
      "optimal_threshold": 0.39564821124076843,
      "tpr_at_fpr_0_01": 0.3,
      "fpr95": 0.628,
      "aupr": 0.8777982142901077
    },
    "layer_31": {
      "n_total": 500,
      "n_valid": 500,
      "n_val_total": 500,
      "n_val_valid": 500,
      "acc": 0.796,
      "f1": 0.7901234567901234,
      "pre": 0.8135593220338984,
      "recall": 0.768,
      "auroc": 0.87024,
      "optimal_threshold": 0.4115471839904785,
      "tpr_at_fpr_0_01": 0.252,
      "fpr95": 0.592,
      "aupr": 0.8751778078437916
    },
    "layer_32": {
      "n_total": 500,
      "n_valid": 500,
      "n_val_total": 500,
      "n_val_valid": 500,
      "acc": 0.812,
      "f1": 0.8073770491803278,
      "pre": 0.8277310924369747,
      "recall": 0.788,
      "auroc": 0.882112,
      "optimal_threshold": 0.41127559542655945,
      "tpr_at_fpr_0_01": 0.312,
      "fpr95": 0.52,
      "aupr": 0.8863457031301081
    },
    "layer_33": {
      "n_total": 500,
      "n_valid": 500,
      "n_val_total": 500,
      "n_val_valid": 500,
      "acc": 0.768,
      "f1": 0.7531914893617021,
      "pre": 0.8045454545454546,
      "recall": 0.708,
      "auroc": 0.870464,
      "optimal_threshold": 0.4907098412513733,
      "tpr_at_fpr_0_01": 0.364,
      "fpr95": 0.54,
      "aupr": 0.8815319079276567
    }
  },
  "metrics_avg_projection": {
    "n_total": 500,
    "n_valid": 500,
    "n_val_total": 500,
    "n_val_valid": 500,
    "acc": 0.792,
    "f1": 0.7992277992277992,
    "pre": 0.7723880597014925,
    "recall": 0.828,
    "auroc": 0.86832,
    "optimal_threshold": 0.32843223214149475,
    "tpr_at_fpr_0_01": 0.372,
    "fpr95": 0.596,
    "aupr": 0.8830909572350251
  },
  "metrics_avg_projection_div_std": {
    "n_total": 500,
    "n_valid": 500,
    "n_val_total": 500,
    "n_val_valid": 500,
    "acc": 0.75,
    "f1": 0.7346072186836518,
    "pre": 0.7828054298642534,
    "recall": 0.692,
    "auroc": 0.814384,
    "optimal_threshold": 6.053508281707764,
    "tpr_at_fpr_0_01": 0.172,
    "fpr95": 0.756,
    "aupr": 0.8308051761224716
  },
  "metrics_avg_projection_last_2_3_layers": {
    "n_total": 500,
    "n_valid": 500,
    "n_val_total": 500,
    "n_val_valid": 500,
    "acc": 0.792,
    "f1": 0.7944664031620553,
    "pre": 0.78515625,
    "recall": 0.804,
    "auroc": 0.8672959999999998,
    "optimal_threshold": 0.34186050295829773,
    "tpr_at_fpr_0_01": 0.348,
    "fpr95": 0.668,
    "aupr": 0.8814254598458671
  },
  "metrics_avg_projection_div_std_last_2_3_layers": {
    "n_total": 500,
    "n_valid": 500,
    "n_val_total": 500,
    "n_val_valid": 500,
    "acc": 0.73,
    "f1": 0.7169811320754716,
    "pre": 0.7533039647577092,
    "recall": 0.684,
    "auroc": 0.791232,
    "optimal_threshold": 9.342533111572266,
    "tpr_at_fpr_0_01": 0.108,
    "fpr95": 0.844,
    "aupr": 0.804696986539219
  }
}